{
  "kind": "collectionType",
  "collectionName": "categories",
  "info": {
    "singularName": "category",
    "pluralName": "categories",
    "displayName": "Category",
    "description": ""
  },
  "options": {
    "draftAndPublish": true
  },
  "pluginOptions": {},
  "attributes": {
    "title": {
      "type": "string"
    },
    "image": {
      "type": "media",
      "multiple": false,
      "required": false,
      "allowedTypes": [
        "images",
        "files",
        "videos",
        "audios"
      ]
    },
    "color": {
      "type": "string"
    },
    "titleBtn": {
      "type": "string"
    },
    "type": {
      "type": "string"
    },
    "keyboards": {
      "type": "relation",
      "relation": "oneToMany",
      "target": "api::keyboard.keyboard",
      "mappedBy": "category"
    },
    "battaries": {
      "type": "relation",
      "relation": "oneToMany",
      "target": "api::battary.battary",
      "mappedBy": "category"
    },
    "matrices": {
      "type": "relation",
      "relation": "oneToMany",
      "target": "api::matrix.matrix",
      "mappedBy": "category"
    }
  }
}
